dbtpurview/__init__.py
dbtpurview/main.py
dbt_purview-0.56.dist-info/METADATA
dbt_purview-0.56.dist-info/WHEEL
dbt_purview-0.56.dist-info/entry_points.txt
dbt_purview-0.56.dist-info/top_level.txt
dbt_purview-0.56.dist-info/RECORD
