Metadata-Version: 2.1
Name: dbt-purview
Version: 0.56
Requires-Dist: click
Requires-Dist: requests
Requires-Dist: apache-airflow
